Metadata-Version: 1.0
Name: dash-dagre
Version: 0.0.2
Summary: Project Description
Home-page: UNKNOWN
Author: BenJoyenConseil b.joyenconseil@gmail.com
Author-email: UNKNOWN
License: MIT
Platform: UNKNOWN
